pytadarida/__init__.py
pytadarida/commands.py
pytadarida/configs.py
pytadarida/logs.py
pytadarida/output.py
pytadarida/parsing.py
pytadarida/validate_inputs.py
pytadarida/TadaridaD/LICENSE
pytadarida/TadaridaD/TadaridaD
pytadarida/TadaridaD/libQt5Core.so.5
pytadarida/TadaridaD/libfftw3f.so
pytadarida/TadaridaD/libicudata.so.54
pytadarida/TadaridaD/libicuuc.so.54
pytadarida/TadaridaD/libsndfile.so
pytadarida-0.1.0.dist-info/METADATA
pytadarida-0.1.0.dist-info/WHEEL
pytadarida-0.1.0.dist-info/licenses/LICENSE
pytadarida-0.1.0.dist-info/RECORD
