Metadata-Version: 2.1
Name: pytadarida
Version: 0.1.0
Summary: Python wrapper to Tadarida-D software
Author-email: Santiago Martinez <santiago.mbal@gmail.com>
License: MIT
License-File: LICENSE
Requires-Python: >=3.8
Requires-Dist: pandas>=1.5.3
